README.md
setup.py
haven/__init__.py
haven/haven_chk.py
haven/haven_dropbox.py
haven/haven_gdrive.py
haven/haven_img.py
haven/haven_jobs.py
haven/haven_jupyter.py
haven/haven_results.py
haven/haven_utils.py
havenai.egg-info/PKG-INFO
havenai.egg-info/SOURCES.txt
havenai.egg-info/dependency_links.txt
havenai.egg-info/not-zip-safe
havenai.egg-info/requires.txt
havenai.egg-info/top_level.txt