Metadata-Version: 1.2
Name: havenai
Version: 0.5.0
Summary: Manage large-scale experiments
Home-page: https://github.com/ElementAI/haven
Maintainer: Issam Laradji
Maintainer-email: issam.laradji@elementai.com
License: MIT
Platform: UNKNOWN
